consistent_sampler/__init__.py
consistent_sampler/consistent_sampler.py
consistent_sampler/demo_consistent_sampler.py
consistent_sampler/test_consistent_sampler.py
consistent_sampler-1.0.10.dist-info/METADATA
consistent_sampler-1.0.10.dist-info/RECORD
consistent_sampler-1.0.10.dist-info/WHEEL
consistent_sampler-1.0.10.dist-info/top_level.txt
