Metadata-Version: 2.1
Name: consistent-sampler
Version: 1.0.10
Summary: Package for consistent sampling with or without replacement.
Home-page: https://github.com/ron-rivest/consistent_sampler
Author: Ronald L. Rivest
Author-email: rivest@mit.edu
License: MIT License
Platform: UNKNOWN
Classifier: Programming Language :: Python :: 3
Classifier: License :: OSI Approved :: MIT License
Classifier: Operating System :: OS Independent
